rotary_slider.py
circuitpython_rotary_slider-0.1.0.dist-info/LICENSE
circuitpython_rotary_slider-0.1.0.dist-info/METADATA
circuitpython_rotary_slider-0.1.0.dist-info/WHEEL
circuitpython_rotary_slider-0.1.0.dist-info/top_level.txt
circuitpython_rotary_slider-0.1.0.dist-info/RECORD
