Metadata-Version: 2.1
Name: circuitpython-rotary-slider
Version: 0.1.0
Summary: Displayio Layout Rotary Slider Widget
Author-email: "Jose D. Montoya" <jlib@mailmeto.mozmail.com>
License: MIT
Project-URL: Homepage, https://github.com/jposada202020/CircuitPython_Rotary_Slider
Keywords: sensor,blinka,circuitpython,micropython,rotary_slider,displayio,widget,control,rotary,layout
Classifier: Intended Audience :: Developers
Classifier: Topic :: Software Development :: Libraries
Classifier: Topic :: Software Development :: Embedded Systems
Classifier: Topic :: System :: Hardware
Classifier: License :: OSI Approved :: MIT License
Classifier: Programming Language :: Python :: 3
License-File: LICENSE
Requires-Dist: Adafruit-Blinka
Requires-Dist: adafruit-circuitpython-busdevice
Requires-Dist: adafruit-circuitpython-register
Provides-Extra: optional
